jayna/__init__.py
jayna/main.py
jayna/drawing/__init__.py
jayna/drawing/bunny.py
jayna/drawing/sunset.py
jayna/utils/__init__.py
jayna/utils/birfday.py
jayna-0.1.2.dist-info/LICENSE
jayna-0.1.2.dist-info/METADATA
jayna-0.1.2.dist-info/WHEEL
jayna-0.1.2.dist-info/top_level.txt
jayna-0.1.2.dist-info/RECORD
