Metadata-Version: 2.1
Name: jayna
Version: 0.1.2
Summary: A jayna package
Home-page: https://github.com/jhuang1723/jayna
Author: Jayna
Author-email: jaynahuang@gmail.com
Classifier: Programming Language :: Python :: 3
Classifier: License :: OSI Approved :: MIT License
Classifier: Operating System :: OS Independent
Requires-Python: >=3.6
License-File: LICENSE
